README.md
setup.cfg
setup.py
bilibiliSpiderSet/__init__.py
bilibiliSpiderSet/color_logger.py
bilibiliSpiderSet/info.py
bilibiliSpiderSet/main.py
bilibiliSpiderSet/spider_set.py
bilibiliSpiderSet.egg-info/PKG-INFO
bilibiliSpiderSet.egg-info/SOURCES.txt
bilibiliSpiderSet.egg-info/dependency_links.txt
bilibiliSpiderSet.egg-info/entry_points.txt
bilibiliSpiderSet.egg-info/not-zip-safe
bilibiliSpiderSet.egg-info/requires.txt
bilibiliSpiderSet.egg-info/top_level.txt