Metadata-Version: 1.0
Name: bilibiliSpiderSet
Version: 0.1.22
Summary: A set of useful bilibili spider
Home-page: https://github.com/Haut-Stone
Author: Jiahuan Shi
Author-email: redstonerock149@gmail.com
License: MIT License
Platform: UNKNOWN
